{
  "run_id": "b5a83277",
  "timestamp": "2026-06-09T01:55:45.883038+00:00",
  "classifier": "random-forest",
  "dataset": "minecraft",
  "preprocessor": "khan",
  "splitter": "half",
  "preprocessor_window_size": 200,
  "is_debug": false,
  "user_results": [
    {
      "user_id": "0",
      "score": 0.71875,
      "balanced_score": 0.71875,
      "f1_macro": 0.41818181818181815,
      "f1_weighted": 0.8363636363636363,
      "precision_macro": 0.5,
      "recall_macro": 0.359375,
      "best_params": {
        "bootstrap": true,
        "ccp_alpha": 0.0,
        "class_weight": "balanced",
        "criterion": "entropy",
        "max_depth": 15,
        "max_features": 0.5,
        "max_leaf_nodes": null,
        "max_samples": 0.980669655444389,
        "min_impurity_decrease": 0.0,
        "min_samples_leaf": 12,
        "min_samples_split": 19,
        "min_weight_fraction_leaf": 0.0,
        "monotonic_cst": null,
        "n_estimators": 250,
        "n_jobs": null,
        "oob_score": false,
        "random_state": 42,
        "verbose": 0,
        "warm_start": false
      }
    },
    {
      "user_id": "1",
      "score": 0.6216216216216216,
      "balanced_score": 0.6216216216216216,
      "f1_macro": 0.38333333333333336,
      "f1_weighted": 0.7666666666666667,
      "precision_macro": 0.5,
      "recall_macro": 0.3108108108108108,
      "best_params": {
        "bootstrap": false,
        "ccp_alpha": 0.0,
        "class_weight": "balanced_subsample",
        "criterion": "entropy",
        "max_depth": 18,
        "max_features": "sqrt",
        "max_leaf_nodes": null,
        "max_samples": null,
        "min_impurity_decrease": 0.0,
        "min_samples_leaf": 9,
        "min_samples_split": 4,
        "min_weight_fraction_leaf": 0.0,
        "monotonic_cst": null,
        "n_estimators": 100,
        "n_jobs": null,
        "oob_score": false,
        "random_state": 42,
        "verbose": 0,
        "warm_start": false
      }
    },
    {
      "user_id": "2",
      "score": 0.7428571428571429,
      "balanced_score": 0.7428571428571429,
      "f1_macro": 0.4262295081967213,
      "f1_weighted": 0.8524590163934426,
      "precision_macro": 0.5,
      "recall_macro": 0.37142857142857144,
      "best_params": {
        "bootstrap": true,
        "ccp_alpha": 0.0,
        "class_weight": "balanced",
        "criterion": "entropy",
        "max_depth": 6,
        "max_features": "log2",
        "max_leaf_nodes": null,
        "max_samples": 0.9968820575931776,
        "min_impurity_decrease": 0.0,
        "min_samples_leaf": 13,
        "min_samples_split": 13,
        "min_weight_fraction_leaf": 0.0,
        "monotonic_cst": null,
        "n_estimators": 100,
        "n_jobs": null,
        "oob_score": false,
        "random_state": 42,
        "verbose": 0,
        "warm_start": false
      }
    },
    {
      "user_id": "3",
      "score": 0.7291666666666666,
      "balanced_score": 0.7291666666666666,
      "f1_macro": 0.42168674698795183,
      "f1_weighted": 0.8433734939759038,
      "precision_macro": 0.5,
      "recall_macro": 0.3645833333333333,
      "best_params": {
        "bootstrap": true,
        "ccp_alpha": 0.0,
        "class_weight": "balanced_subsample",
        "criterion": "entropy",
        "max_depth": 10,
        "max_features": "log2",
        "max_leaf_nodes": null,
        "max_samples": 0.7482030397613695,
        "min_impurity_decrease": 0.0,
        "min_samples_leaf": 3,
        "min_samples_split": 6,
        "min_weight_fraction_leaf": 0.0,
        "monotonic_cst": null,
        "n_estimators": 200,
        "n_jobs": null,
        "oob_score": false,
        "random_state": 42,
        "verbose": 0,
        "warm_start": false
      }
    },
    {
      "user_id": "4",
      "score": 0.7368421052631579,
      "balanced_score": 0.7368421052631579,
      "f1_macro": 0.42424242424242425,
      "f1_weighted": 0.8484848484848485,
      "precision_macro": 0.5,
      "recall_macro": 0.3684210526315789,
      "best_params": {
        "bootstrap": true,
        "ccp_alpha": 0.0,
        "class_weight": "balanced",
        "criterion": "entropy",
        "max_depth": 16,
        "max_features": "sqrt",
        "max_leaf_nodes": null,
        "max_samples": 0.7418247660433059,
        "min_impurity_decrease": 0.0,
        "min_samples_leaf": 8,
        "min_samples_split": 19,
        "min_weight_fraction_leaf": 0.0,
        "monotonic_cst": null,
        "n_estimators": 250,
        "n_jobs": null,
        "oob_score": false,
        "random_state": 42,
        "verbose": 0,
        "warm_start": false
      }
    },
    {
      "user_id": "5",
      "score": 0.6774193548387096,
      "balanced_score": 0.6774193548387096,
      "f1_macro": 0.40384615384615385,
      "f1_weighted": 0.8076923076923077,
      "precision_macro": 0.5,
      "recall_macro": 0.3387096774193548,
      "best_params": {
        "bootstrap": false,
        "ccp_alpha": 0.0,
        "class_weight": "balanced",
        "criterion": "entropy",
        "max_depth": 6,
        "max_features": 0.5,
        "max_leaf_nodes": null,
        "max_samples": null,
        "min_impurity_decrease": 0.0,
        "min_samples_leaf": 9,
        "min_samples_split": 3,
        "min_weight_fraction_leaf": 0.0,
        "monotonic_cst": null,
        "n_estimators": 150,
        "n_jobs": null,
        "oob_score": false,
        "random_state": 42,
        "verbose": 0,
        "warm_start": false
      }
    },
    {
      "user_id": "6",
      "score": 0.8148148148148148,
      "balanced_score": 0.8148148148148148,
      "f1_macro": 0.4489795918367347,
      "f1_weighted": 0.8979591836734694,
      "precision_macro": 0.5,
      "recall_macro": 0.4074074074074074,
      "best_params": {
        "bootstrap": false,
        "ccp_alpha": 0.0,
        "class_weight": "balanced",
        "criterion": "entropy",
        "max_depth": 14,
        "max_features": "log2",
        "max_leaf_nodes": null,
        "max_samples": null,
        "min_impurity_decrease": 0.0,
        "min_samples_leaf": 1,
        "min_samples_split": 13,
        "min_weight_fraction_leaf": 0.0,
        "monotonic_cst": null,
        "n_estimators": 250,
        "n_jobs": null,
        "oob_score": false,
        "random_state": 42,
        "verbose": 0,
        "warm_start": false
      }
    },
    {
      "user_id": "7",
      "score": 0.6923076923076923,
      "balanced_score": 0.6923076923076923,
      "f1_macro": 0.4090909090909091,
      "f1_weighted": 0.8181818181818182,
      "precision_macro": 0.5,
      "recall_macro": 0.34615384615384615,
      "best_params": {
        "bootstrap": true,
        "ccp_alpha": 0.0,
        "class_weight": null,
        "criterion": "gini",
        "max_depth": 11,
        "max_features": "log2",
        "max_leaf_nodes": null,
        "max_samples": 0.5765412411286985,
        "min_impurity_decrease": 0.0,
        "min_samples_leaf": 2,
        "min_samples_split": 20,
        "min_weight_fraction_leaf": 0.0,
        "monotonic_cst": null,
        "n_estimators": 200,
        "n_jobs": null,
        "oob_score": false,
        "random_state": 42,
        "verbose": 0,
        "warm_start": false
      }
    },
    {
      "user_id": "8",
      "score": 0.6896551724137931,
      "balanced_score": 0.6896551724137931,
      "f1_macro": 0.40816326530612246,
      "f1_weighted": 0.8163265306122449,
      "precision_macro": 0.5,
      "recall_macro": 0.3448275862068966,
      "best_params": {
        "bootstrap": true,
        "ccp_alpha": 0.0,
        "class_weight": "balanced",
        "criterion": "gini",
        "max_depth": 7,
        "max_features": "log2",
        "max_leaf_nodes": null,
        "max_samples": 0.876901926232787,
        "min_impurity_decrease": 0.0,
        "min_samples_leaf": 7,
        "min_samples_split": 10,
        "min_weight_fraction_leaf": 0.0,
        "monotonic_cst": null,
        "n_estimators": 200,
        "n_jobs": null,
        "oob_score": false,
        "random_state": 42,
        "verbose": 0,
        "warm_start": false
      }
    },
    {
      "user_id": "9",
      "score": 0.7692307692307693,
      "balanced_score": 0.7692307692307693,
      "f1_macro": 0.43478260869565216,
      "f1_weighted": 0.8695652173913043,
      "precision_macro": 0.5,
      "recall_macro": 0.38461538461538464,
      "best_params": {
        "bootstrap": false,
        "ccp_alpha": 0.0,
        "class_weight": "balanced",
        "criterion": "gini",
        "max_depth": 13,
        "max_features": 0.5,
        "max_leaf_nodes": null,
        "max_samples": null,
        "min_impurity_decrease": 0.0,
        "min_samples_leaf": 14,
        "min_samples_split": 9,
        "min_weight_fraction_leaf": 0.0,
        "monotonic_cst": null,
        "n_estimators": 300,
        "n_jobs": null,
        "oob_score": false,
        "random_state": 42,
        "verbose": 0,
        "warm_start": false
      }
    },
    {
      "user_id": "10",
      "score": 0.7941176470588235,
      "balanced_score": 0.7941176470588235,
      "f1_macro": 0.4426229508196721,
      "f1_weighted": 0.8852459016393442,
      "precision_macro": 0.5,
      "recall_macro": 0.39705882352941174,
      "best_params": {
        "bootstrap": true,
        "ccp_alpha": 0.0,
        "class_weight": null,
        "criterion": "gini",
        "max_depth": 17,
        "max_features": 0.5,
        "max_leaf_nodes": null,
        "max_samples": 0.5261114442806638,
        "min_impurity_decrease": 0.0,
        "min_samples_leaf": 14,
        "min_samples_split": 11,
        "min_weight_fraction_leaf": 0.0,
        "monotonic_cst": null,
        "n_estimators": 300,
        "n_jobs": null,
        "oob_score": false,
        "random_state": 42,
        "verbose": 0,
        "warm_start": false
      }
    },
    {
      "user_id": "11",
      "score": 0.8048780487804879,
      "balanced_score": 0.8048780487804879,
      "f1_macro": 0.44594594594594594,
      "f1_weighted": 0.8918918918918918,
      "precision_macro": 0.5,
      "recall_macro": 0.4024390243902439,
      "best_params": {
        "bootstrap": true,
        "ccp_alpha": 0.0,
        "class_weight": null,
        "criterion": "gini",
        "max_depth": 14,
        "max_features": "sqrt",
        "max_leaf_nodes": null,
        "max_samples": 0.9266354872161913,
        "min_impurity_decrease": 0.0,
        "min_samples_leaf": 14,
        "min_samples_split": 11,
        "min_weight_fraction_leaf": 0.0,
        "monotonic_cst": null,
        "n_estimators": 400,
        "n_jobs": null,
        "oob_score": false,
        "random_state": 42,
        "verbose": 0,
        "warm_start": false
      }
    },
    {
      "user_id": "12",
      "score": 0.7894736842105263,
      "balanced_score": 0.7894736842105263,
      "f1_macro": 0.4411764705882353,
      "f1_weighted": 0.8823529411764707,
      "precision_macro": 0.5,
      "recall_macro": 0.39473684210526316,
      "best_params": {
        "bootstrap": true,
        "ccp_alpha": 0.0,
        "class_weight": "balanced_subsample",
        "criterion": "entropy",
        "max_depth": 7,
        "max_features": "log2",
        "max_leaf_nodes": null,
        "max_samples": 0.7997430239535952,
        "min_impurity_decrease": 0.0,
        "min_samples_leaf": 2,
        "min_samples_split": 11,
        "min_weight_fraction_leaf": 0.0,
        "monotonic_cst": null,
        "n_estimators": 200,
        "n_jobs": null,
        "oob_score": false,
        "random_state": 42,
        "verbose": 0,
        "warm_start": false
      }
    },
    {
      "user_id": "13",
      "score": 0.7435897435897436,
      "balanced_score": 0.7435897435897436,
      "f1_macro": 0.4264705882352941,
      "f1_weighted": 0.8529411764705882,
      "precision_macro": 0.5,
      "recall_macro": 0.3717948717948718,
      "best_params": {
        "bootstrap": false,
        "ccp_alpha": 0.0,
        "class_weight": "balanced_subsample",
        "criterion": "entropy",
        "max_depth": 15,
        "max_features": "log2",
        "max_leaf_nodes": null,
        "max_samples": null,
        "min_impurity_decrease": 0.0,
        "min_samples_leaf": 10,
        "min_samples_split": 10,
        "min_weight_fraction_leaf": 0.0,
        "monotonic_cst": null,
        "n_estimators": 300,
        "n_jobs": null,
        "oob_score": false,
        "random_state": 42,
        "verbose": 0,
        "warm_start": false
      }
    },
    {
      "user_id": "14",
      "score": 0.6086956521739131,
      "balanced_score": 0.6086956521739131,
      "f1_macro": 0.3783783783783784,
      "f1_weighted": 0.7567567567567568,
      "precision_macro": 0.5,
      "recall_macro": 0.30434782608695654,
      "best_params": {
        "bootstrap": true,
        "ccp_alpha": 0.0,
        "class_weight": "balanced",
        "criterion": "gini",
        "max_depth": 12,
        "max_features": "log2",
        "max_leaf_nodes": null,
        "max_samples": 0.521384568679721,
        "min_impurity_decrease": 0.0,
        "min_samples_leaf": 8,
        "min_samples_split": 18,
        "min_weight_fraction_leaf": 0.0,
        "monotonic_cst": null,
        "n_estimators": 350,
        "n_jobs": null,
        "oob_score": false,
        "random_state": 42,
        "verbose": 0,
        "warm_start": false
      }
    },
    {
      "user_id": "15",
      "score": 0.5294117647058824,
      "balanced_score": 0.5294117647058824,
      "f1_macro": 0.34615384615384615,
      "f1_weighted": 0.6923076923076923,
      "precision_macro": 0.5,
      "recall_macro": 0.2647058823529412,
      "best_params": {
        "bootstrap": false,
        "ccp_alpha": 0.0,
        "class_weight": "balanced_subsample",
        "criterion": "entropy",
        "max_depth": 15,
        "max_features": "log2",
        "max_leaf_nodes": null,
        "max_samples": null,
        "min_impurity_decrease": 0.0,
        "min_samples_leaf": 7,
        "min_samples_split": 11,
        "min_weight_fraction_leaf": 0.0,
        "monotonic_cst": null,
        "n_estimators": 250,
        "n_jobs": null,
        "oob_score": false,
        "random_state": 42,
        "verbose": 0,
        "warm_start": false
      }
    },
    {
      "user_id": "16",
      "score": 0.8292682926829268,
      "balanced_score": 0.8292682926829268,
      "f1_macro": 0.4533333333333333,
      "f1_weighted": 0.9066666666666666,
      "precision_macro": 0.5,
      "recall_macro": 0.4146341463414634,
      "best_params": {
        "bootstrap": false,
        "ccp_alpha": 0.0,
        "class_weight": "balanced_subsample",
        "criterion": "gini",
        "max_depth": 10,
        "max_features": "log2",
        "max_leaf_nodes": null,
        "max_samples": null,
        "min_impurity_decrease": 0.0,
        "min_samples_leaf": 3,
        "min_samples_split": 9,
        "min_weight_fraction_leaf": 0.0,
        "monotonic_cst": null,
        "n_estimators": 250,
        "n_jobs": null,
        "oob_score": false,
        "random_state": 42,
        "verbose": 0,
        "warm_start": false
      }
    },
    {
      "user_id": "17",
      "score": 0.6,
      "balanced_score": 0.6,
      "f1_macro": 0.375,
      "f1_weighted": 0.75,
      "precision_macro": 0.5,
      "recall_macro": 0.3,
      "best_params": {
        "bootstrap": false,
        "ccp_alpha": 0.0,
        "class_weight": "balanced_subsample",
        "criterion": "gini",
        "max_depth": 19,
        "max_features": 0.5,
        "max_leaf_nodes": null,
        "max_samples": null,
        "min_impurity_decrease": 0.0,
        "min_samples_leaf": 20,
        "min_samples_split": 20,
        "min_weight_fraction_leaf": 0.0,
        "monotonic_cst": null,
        "n_estimators": 100,
        "n_jobs": null,
        "oob_score": false,
        "random_state": 42,
        "verbose": 0,
        "warm_start": false
      }
    },
    {
      "user_id": "18",
      "score": 0.7727272727272727,
      "balanced_score": 0.7727272727272727,
      "f1_macro": 0.4358974358974359,
      "f1_weighted": 0.8717948717948718,
      "precision_macro": 0.5,
      "recall_macro": 0.38636363636363635,
      "best_params": {
        "bootstrap": false,
        "ccp_alpha": 0.0,
        "class_weight": "balanced",
        "criterion": "entropy",
        "max_depth": 19,
        "max_features": "log2",
        "max_leaf_nodes": null,
        "max_samples": null,
        "min_impurity_decrease": 0.0,
        "min_samples_leaf": 7,
        "min_samples_split": 17,
        "min_weight_fraction_leaf": 0.0,
        "monotonic_cst": null,
        "n_estimators": 100,
        "n_jobs": null,
        "oob_score": false,
        "random_state": 42,
        "verbose": 0,
        "warm_start": false
      }
    },
    {
      "user_id": "19",
      "score": 0.6666666666666666,
      "balanced_score": 0.6666666666666666,
      "f1_macro": 0.4,
      "f1_weighted": 0.8,
      "precision_macro": 0.5,
      "recall_macro": 0.3333333333333333,
      "best_params": {
        "bootstrap": false,
        "ccp_alpha": 0.0,
        "class_weight": "balanced",
        "criterion": "gini",
        "max_depth": 19,
        "max_features": 0.5,
        "max_leaf_nodes": null,
        "max_samples": null,
        "min_impurity_decrease": 0.0,
        "min_samples_leaf": 6,
        "min_samples_split": 6,
        "min_weight_fraction_leaf": 0.0,
        "monotonic_cst": null,
        "n_estimators": 150,
        "n_jobs": null,
        "oob_score": false,
        "random_state": 42,
        "verbose": 0,
        "warm_start": false
      }
    },
    {
      "user_id": "20",
      "score": 0.8125,
      "balanced_score": 0.8125,
      "f1_macro": 0.4482758620689655,
      "f1_weighted": 0.896551724137931,
      "precision_macro": 0.5,
      "recall_macro": 0.40625,
      "best_params": {
        "bootstrap": true,
        "ccp_alpha": 0.0,
        "class_weight": "balanced",
        "criterion": "gini",
        "max_depth": 15,
        "max_features": 0.5,
        "max_leaf_nodes": null,
        "max_samples": 0.5014035933267673,
        "min_impurity_decrease": 0.0,
        "min_samples_leaf": 1,
        "min_samples_split": 9,
        "min_weight_fraction_leaf": 0.0,
        "monotonic_cst": null,
        "n_estimators": 100,
        "n_jobs": null,
        "oob_score": false,
        "random_state": 42,
        "verbose": 0,
        "warm_start": false
      }
    },
    {
      "user_id": "21",
      "score": 0.5806451612903226,
      "balanced_score": 0.5806451612903226,
      "f1_macro": 0.3673469387755102,
      "f1_weighted": 0.7346938775510204,
      "precision_macro": 0.5,
      "recall_macro": 0.2903225806451613,
      "best_params": {
        "bootstrap": false,
        "ccp_alpha": 0.0,
        "class_weight": null,
        "criterion": "gini",
        "max_depth": 12,
        "max_features": "sqrt",
        "max_leaf_nodes": null,
        "max_samples": null,
        "min_impurity_decrease": 0.0,
        "min_samples_leaf": 9,
        "min_samples_split": 9,
        "min_weight_fraction_leaf": 0.0,
        "monotonic_cst": null,
        "n_estimators": 100,
        "n_jobs": null,
        "oob_score": false,
        "random_state": 42,
        "verbose": 0,
        "warm_start": false
      }
    },
    {
      "user_id": "22",
      "score": 0.7804878048780488,
      "balanced_score": 0.7804878048780488,
      "f1_macro": 0.4383561643835616,
      "f1_weighted": 0.8767123287671234,
      "precision_macro": 0.5,
      "recall_macro": 0.3902439024390244,
      "best_params": {
        "bootstrap": true,
        "ccp_alpha": 0.0,
        "class_weight": "balanced_subsample",
        "criterion": "gini",
        "max_depth": 15,
        "max_features": 0.5,
        "max_leaf_nodes": null,
        "max_samples": 0.5902402864278811,
        "min_impurity_decrease": 0.0,
        "min_samples_leaf": 6,
        "min_samples_split": 8,
        "min_weight_fraction_leaf": 0.0,
        "monotonic_cst": null,
        "n_estimators": 300,
        "n_jobs": null,
        "oob_score": false,
        "random_state": 42,
        "verbose": 0,
        "warm_start": false
      }
    },
    {
      "user_id": "23",
      "score": 0.6470588235294118,
      "balanced_score": 0.6470588235294118,
      "f1_macro": 0.39285714285714285,
      "f1_weighted": 0.7857142857142857,
      "precision_macro": 0.5,
      "recall_macro": 0.3235294117647059,
      "best_params": {
        "bootstrap": false,
        "ccp_alpha": 0.0,
        "class_weight": "balanced",
        "criterion": "entropy",
        "max_depth": 16,
        "max_features": 0.5,
        "max_leaf_nodes": null,
        "max_samples": null,
        "min_impurity_decrease": 0.0,
        "min_samples_leaf": 6,
        "min_samples_split": 10,
        "min_weight_fraction_leaf": 0.0,
        "monotonic_cst": null,
        "n_estimators": 250,
        "n_jobs": null,
        "oob_score": false,
        "random_state": 42,
        "verbose": 0,
        "warm_start": false
      }
    },
    {
      "user_id": "24",
      "score": 0.9166666666666666,
      "balanced_score": 0.9166666666666666,
      "f1_macro": 0.4782608695652174,
      "f1_weighted": 0.9565217391304349,
      "precision_macro": 0.5,
      "recall_macro": 0.4583333333333333,
      "best_params": {
        "bootstrap": false,
        "ccp_alpha": 0.0,
        "class_weight": null,
        "criterion": "gini",
        "max_depth": 19,
        "max_features": "log2",
        "max_leaf_nodes": null,
        "max_samples": null,
        "min_impurity_decrease": 0.0,
        "min_samples_leaf": 1,
        "min_samples_split": 9,
        "min_weight_fraction_leaf": 0.0,
        "monotonic_cst": null,
        "n_estimators": 400,
        "n_jobs": null,
        "oob_score": false,
        "random_state": 42,
        "verbose": 0,
        "warm_start": false
      }
    },
    {
      "user_id": "25",
      "score": 0.725,
      "balanced_score": 0.725,
      "f1_macro": 0.42028985507246375,
      "f1_weighted": 0.8405797101449275,
      "precision_macro": 0.5,
      "recall_macro": 0.3625,
      "best_params": {
        "bootstrap": true,
        "ccp_alpha": 0.0,
        "class_weight": "balanced_subsample",
        "criterion": "gini",
        "max_depth": 10,
        "max_features": "sqrt",
        "max_leaf_nodes": null,
        "max_samples": 0.5353226689560693,
        "min_impurity_decrease": 0.0,
        "min_samples_leaf": 4,
        "min_samples_split": 2,
        "min_weight_fraction_leaf": 0.0,
        "monotonic_cst": null,
        "n_estimators": 100,
        "n_jobs": null,
        "oob_score": false,
        "random_state": 42,
        "verbose": 0,
        "warm_start": false
      }
    },
    {
      "user_id": "26",
      "score": 0.875,
      "balanced_score": 0.875,
      "f1_macro": 0.4666666666666667,
      "f1_weighted": 0.9333333333333333,
      "precision_macro": 0.5,
      "recall_macro": 0.4375,
      "best_params": {
        "bootstrap": true,
        "ccp_alpha": 0.0,
        "class_weight": null,
        "criterion": "entropy",
        "max_depth": 14,
        "max_features": "log2",
        "max_leaf_nodes": null,
        "max_samples": 0.8374160446488275,
        "min_impurity_decrease": 0.0,
        "min_samples_leaf": 3,
        "min_samples_split": 2,
        "min_weight_fraction_leaf": 0.0,
        "monotonic_cst": null,
        "n_estimators": 150,
        "n_jobs": null,
        "oob_score": false,
        "random_state": 42,
        "verbose": 0,
        "warm_start": false
      }
    },
    {
      "user_id": "27",
      "score": 0.7941176470588235,
      "balanced_score": 0.7941176470588235,
      "f1_macro": 0.4426229508196721,
      "f1_weighted": 0.8852459016393442,
      "precision_macro": 0.5,
      "recall_macro": 0.39705882352941174,
      "best_params": {
        "bootstrap": false,
        "ccp_alpha": 0.0,
        "class_weight": "balanced_subsample",
        "criterion": "gini",
        "max_depth": 7,
        "max_features": 0.5,
        "max_leaf_nodes": null,
        "max_samples": null,
        "min_impurity_decrease": 0.0,
        "min_samples_leaf": 5,
        "min_samples_split": 3,
        "min_weight_fraction_leaf": 0.0,
        "monotonic_cst": null,
        "n_estimators": 300,
        "n_jobs": null,
        "oob_score": false,
        "random_state": 42,
        "verbose": 0,
        "warm_start": false
      }
    },
    {
      "user_id": "28",
      "score": 0.6857142857142857,
      "balanced_score": 0.6857142857142857,
      "f1_macro": 0.4067796610169492,
      "f1_weighted": 0.8135593220338984,
      "precision_macro": 0.5,
      "recall_macro": 0.34285714285714286,
      "best_params": {
        "bootstrap": true,
        "ccp_alpha": 0.0,
        "class_weight": "balanced_subsample",
        "criterion": "gini",
        "max_depth": 12,
        "max_features": "log2",
        "max_leaf_nodes": null,
        "max_samples": 0.8759138338682113,
        "min_impurity_decrease": 0.0,
        "min_samples_leaf": 12,
        "min_samples_split": 2,
        "min_weight_fraction_leaf": 0.0,
        "monotonic_cst": null,
        "n_estimators": 200,
        "n_jobs": null,
        "oob_score": false,
        "random_state": 42,
        "verbose": 0,
        "warm_start": false
      }
    },
    {
      "user_id": "29",
      "score": 0.7428571428571429,
      "balanced_score": 0.7428571428571429,
      "f1_macro": 0.4262295081967213,
      "f1_weighted": 0.8524590163934426,
      "precision_macro": 0.5,
      "recall_macro": 0.37142857142857144,
      "best_params": {
        "bootstrap": false,
        "ccp_alpha": 0.0,
        "class_weight": "balanced_subsample",
        "criterion": "gini",
        "max_depth": 10,
        "max_features": "log2",
        "max_leaf_nodes": null,
        "max_samples": null,
        "min_impurity_decrease": 0.0,
        "min_samples_leaf": 2,
        "min_samples_split": 20,
        "min_weight_fraction_leaf": 0.0,
        "monotonic_cst": null,
        "n_estimators": 250,
        "n_jobs": null,
        "oob_score": false,
        "random_state": 42,
        "verbose": 0,
        "warm_start": false
      }
    },
    {
      "user_id": "30",
      "score": 0.7878787878787878,
      "balanced_score": 0.7878787878787878,
      "f1_macro": 0.4406779661016949,
      "f1_weighted": 0.8813559322033898,
      "precision_macro": 0.5,
      "recall_macro": 0.3939393939393939,
      "best_params": {
        "bootstrap": false,
        "ccp_alpha": 0.0,
        "class_weight": "balanced",
        "criterion": "entropy",
        "max_depth": 13,
        "max_features": 0.5,
        "max_leaf_nodes": null,
        "max_samples": null,
        "min_impurity_decrease": 0.0,
        "min_samples_leaf": 7,
        "min_samples_split": 2,
        "min_weight_fraction_leaf": 0.0,
        "monotonic_cst": null,
        "n_estimators": 300,
        "n_jobs": null,
        "oob_score": false,
        "random_state": 42,
        "verbose": 0,
        "warm_start": false
      }
    },
    {
      "user_id": "31",
      "score": 0.7735849056603774,
      "balanced_score": 0.7735849056603774,
      "f1_macro": 0.43617021276595747,
      "f1_weighted": 0.8723404255319149,
      "precision_macro": 0.5,
      "recall_macro": 0.3867924528301887,
      "best_params": {
        "bootstrap": true,
        "ccp_alpha": 0.0,
        "class_weight": "balanced",
        "criterion": "gini",
        "max_depth": 10,
        "max_features": "sqrt",
        "max_leaf_nodes": null,
        "max_samples": 0.8819149096851893,
        "min_impurity_decrease": 0.0,
        "min_samples_leaf": 1,
        "min_samples_split": 12,
        "min_weight_fraction_leaf": 0.0,
        "monotonic_cst": null,
        "n_estimators": 350,
        "n_jobs": null,
        "oob_score": false,
        "random_state": 42,
        "verbose": 0,
        "warm_start": false
      }
    },
    {
      "user_id": "32",
      "score": 0.8529411764705882,
      "balanced_score": 0.8529411764705882,
      "f1_macro": 0.4603174603174603,
      "f1_weighted": 0.9206349206349206,
      "precision_macro": 0.5,
      "recall_macro": 0.4264705882352941,
      "best_params": {
        "bootstrap": true,
        "ccp_alpha": 0.0,
        "class_weight": "balanced",
        "criterion": "gini",
        "max_depth": 7,
        "max_features": "log2",
        "max_leaf_nodes": null,
        "max_samples": 0.8684436042377444,
        "min_impurity_decrease": 0.0,
        "min_samples_leaf": 15,
        "min_samples_split": 16,
        "min_weight_fraction_leaf": 0.0,
        "monotonic_cst": null,
        "n_estimators": 100,
        "n_jobs": null,
        "oob_score": false,
        "random_state": 42,
        "verbose": 0,
        "warm_start": false
      }
    },
    {
      "user_id": "33",
      "score": 0.8648648648648649,
      "balanced_score": 0.8648648648648649,
      "f1_macro": 0.463768115942029,
      "f1_weighted": 0.9275362318840581,
      "precision_macro": 0.5,
      "recall_macro": 0.43243243243243246,
      "best_params": {
        "bootstrap": false,
        "ccp_alpha": 0.0,
        "class_weight": "balanced",
        "criterion": "entropy",
        "max_depth": 5,
        "max_features": "sqrt",
        "max_leaf_nodes": null,
        "max_samples": null,
        "min_impurity_decrease": 0.0,
        "min_samples_leaf": 1,
        "min_samples_split": 10,
        "min_weight_fraction_leaf": 0.0,
        "monotonic_cst": null,
        "n_estimators": 350,
        "n_jobs": null,
        "oob_score": false,
        "random_state": 42,
        "verbose": 0,
        "warm_start": false
      }
    },
    {
      "user_id": "34",
      "score": 0.7317073170731707,
      "balanced_score": 0.7317073170731707,
      "f1_macro": 0.4225352112676056,
      "f1_weighted": 0.8450704225352114,
      "precision_macro": 0.5,
      "recall_macro": 0.36585365853658536,
      "best_params": {
        "bootstrap": true,
        "ccp_alpha": 0.0,
        "class_weight": null,
        "criterion": "gini",
        "max_depth": 20,
        "max_features": "sqrt",
        "max_leaf_nodes": null,
        "max_samples": 0.6450391933259099,
        "min_impurity_decrease": 0.0,
        "min_samples_leaf": 3,
        "min_samples_split": 14,
        "min_weight_fraction_leaf": 0.0,
        "monotonic_cst": null,
        "n_estimators": 400,
        "n_jobs": null,
        "oob_score": false,
        "random_state": 42,
        "verbose": 0,
        "warm_start": false
      }
    },
    {
      "user_id": "35",
      "score": 0.7931034482758621,
      "balanced_score": 0.7931034482758621,
      "f1_macro": 0.4423076923076923,
      "f1_weighted": 0.8846153846153846,
      "precision_macro": 0.5,
      "recall_macro": 0.39655172413793105,
      "best_params": {
        "bootstrap": false,
        "ccp_alpha": 0.0,
        "class_weight": "balanced",
        "criterion": "gini",
        "max_depth": 5,
        "max_features": 0.5,
        "max_leaf_nodes": null,
        "max_samples": null,
        "min_impurity_decrease": 0.0,
        "min_samples_leaf": 7,
        "min_samples_split": 19,
        "min_weight_fraction_leaf": 0.0,
        "monotonic_cst": null,
        "n_estimators": 100,
        "n_jobs": null,
        "oob_score": false,
        "random_state": 42,
        "verbose": 0,
        "warm_start": false
      }
    },
    {
      "user_id": "36",
      "score": 0.717391304347826,
      "balanced_score": 0.717391304347826,
      "f1_macro": 0.4177215189873418,
      "f1_weighted": 0.8354430379746836,
      "precision_macro": 0.5,
      "recall_macro": 0.358695652173913,
      "best_params": {
        "bootstrap": true,
        "ccp_alpha": 0.0,
        "class_weight": "balanced_subsample",
        "criterion": "entropy",
        "max_depth": 7,
        "max_features": "sqrt",
        "max_leaf_nodes": null,
        "max_samples": 0.5263863932224695,
        "min_impurity_decrease": 0.0,
        "min_samples_leaf": 13,
        "min_samples_split": 10,
        "min_weight_fraction_leaf": 0.0,
        "monotonic_cst": null,
        "n_estimators": 200,
        "n_jobs": null,
        "oob_score": false,
        "random_state": 42,
        "verbose": 0,
        "warm_start": false
      }
    },
    {
      "user_id": "37",
      "score": 0.8478260869565217,
      "balanced_score": 0.8478260869565217,
      "f1_macro": 0.4588235294117647,
      "f1_weighted": 0.9176470588235294,
      "precision_macro": 0.5,
      "recall_macro": 0.42391304347826086,
      "best_params": {
        "bootstrap": false,
        "ccp_alpha": 0.0,
        "class_weight": null,
        "criterion": "gini",
        "max_depth": 14,
        "max_features": "sqrt",
        "max_leaf_nodes": null,
        "max_samples": null,
        "min_impurity_decrease": 0.0,
        "min_samples_leaf": 6,
        "min_samples_split": 4,
        "min_weight_fraction_leaf": 0.0,
        "monotonic_cst": null,
        "n_estimators": 400,
        "n_jobs": null,
        "oob_score": false,
        "random_state": 42,
        "verbose": 0,
        "warm_start": false
      }
    },
    {
      "user_id": "38",
      "score": 0.75,
      "balanced_score": 0.75,
      "f1_macro": 0.42857142857142855,
      "f1_weighted": 0.8571428571428572,
      "precision_macro": 0.5,
      "recall_macro": 0.375,
      "best_params": {
        "bootstrap": false,
        "ccp_alpha": 0.0,
        "class_weight": "balanced_subsample",
        "criterion": "gini",
        "max_depth": 13,
        "max_features": "log2",
        "max_leaf_nodes": null,
        "max_samples": null,
        "min_impurity_decrease": 0.0,
        "min_samples_leaf": 8,
        "min_samples_split": 18,
        "min_weight_fraction_leaf": 0.0,
        "monotonic_cst": null,
        "n_estimators": 100,
        "n_jobs": null,
        "oob_score": false,
        "random_state": 42,
        "verbose": 0,
        "warm_start": false
      }
    },
    {
      "user_id": "39",
      "score": 0.4230769230769231,
      "balanced_score": 0.4230769230769231,
      "f1_macro": 0.2972972972972973,
      "f1_weighted": 0.5945945945945946,
      "precision_macro": 0.5,
      "recall_macro": 0.21153846153846154,
      "best_params": {
        "bootstrap": false,
        "ccp_alpha": 0.0,
        "class_weight": null,
        "criterion": "entropy",
        "max_depth": 14,
        "max_features": 0.5,
        "max_leaf_nodes": null,
        "max_samples": null,
        "min_impurity_decrease": 0.0,
        "min_samples_leaf": 2,
        "min_samples_split": 9,
        "min_weight_fraction_leaf": 0.0,
        "monotonic_cst": null,
        "n_estimators": 200,
        "n_jobs": null,
        "oob_score": false,
        "random_state": 42,
        "verbose": 0,
        "warm_start": false
      }
    }
  ],
  "mean_score": 0.7358479114802557,
  "mean_balanced_score": 0.7358479114802557,
  "mean_f1_macro": 0.4219847840365776,
  "mean_f1_weighted": 0.8439695680731552,
  "mean_precision_macro": 0.5,
  "mean_recall_macro": 0.3679239557401279,
  "n_users": 40,
  "n_users_skipped": 0
}